denario_app/app.py
denario_app/cli.py
denario_app/components.py
denario_app/constants.py
denario_app/utils.py
denario_app-1.0.0.dist-info/licenses/LICENSE
denario_app-1.0.0.dist-info/METADATA
denario_app-1.0.0.dist-info/WHEEL
denario_app-1.0.0.dist-info/top_level.txt
denario_app-1.0.0.dist-info/RECORD
