Metadata-Version: 2.4
Name: denario_app
Version: 1.0.0
Summary: GUI for the multiagent research assistant Denario
Maintainer-email: Denario <denario.astropilot.ai@gmail.com>
License: GPLv3
Requires-Python: <3.14,>=3.12
License-File: LICENSE
Requires-Dist: streamlit
Requires-Dist: streamlit-pdf-viewer>=0.0.23
Requires-Dist: denario>=1.0.0
Dynamic: license-file
